hermes_langlib/__init__.py
hermes_langlib/caching.py
hermes_langlib/datasets/__init__.py
hermes_langlib/formatter.py
hermes_langlib/locales/__init__.py
hermes_langlib/storage/__init__.py
hermes_langlib/storage/base.py
hermes_langlib/storage/config_provider.py
hermes_langlib/storage/loader.py
hermes_langlib/storage/locale_store.py
hermes_langlib/translators/__init__.py
hermes_langlib/translators/providers.py
hermes_langlib/utils/__init__.py
hermes_langlib/utils/_patterns.py
hermes_langlib-0.1.4.dist-info/LICENSE
hermes_langlib-0.1.4.dist-info/METADATA
hermes_langlib-0.1.4.dist-info/WHEEL
hermes_langlib-0.1.4.dist-info/RECORD
