Metadata-Version: 2.3
Name: hermes_langlib
Version: 0.1.4
Summary: Fast, optimized and high-performance, high-load oriented library for i18n and l10n
License: GNU LGPL 2.1
Author: alexeev-prog
Author-email: alexeev.dev@mail.ru
Requires-Python: >=3.9,<4.0
Classifier: License :: Other/Proprietary License
Classifier: Programming Language :: Python :: 3
Classifier: Programming Language :: Python :: 3.9
Classifier: Programming Language :: Python :: 3.10
Classifier: Programming Language :: Python :: 3.11
Classifier: Programming Language :: Python :: 3.12
Classifier: Programming Language :: Python :: 3.13
Requires-Dist: configparser (>=7.1.0,<8.0.0)
Requires-Dist: deep-translator (>=1.11.4,<2.0.0)
Requires-Dist: orjson (>=3.10.12,<4.0.0)
Requires-Dist: pyyaml (>=6.0.2,<7.0.0)
Requires-Dist: requests (>=2.32.3,<3.0.0)
Requires-Dist: rich (>=14.0.0,<15.0.0)
Requires-Dist: toml (>=0.10.2,<0.11.0)
